odoo/addons/stock_push_delay/README.rst
odoo/addons/stock_push_delay/__init__.py
odoo/addons/stock_push_delay/__manifest__.py
odoo/addons/stock_push_delay/i18n/it.po
odoo/addons/stock_push_delay/i18n/stock_push_delay.pot
odoo/addons/stock_push_delay/models/__init__.py
odoo/addons/stock_push_delay/models/stock_move.py
odoo/addons/stock_push_delay/models/stock_picking.py
odoo/addons/stock_push_delay/readme/CONTRIBUTORS.rst
odoo/addons/stock_push_delay/readme/DESCRIPTION.rst
odoo/addons/stock_push_delay/readme/USAGE.rst
odoo/addons/stock_push_delay/static/description/icon.png
odoo/addons/stock_push_delay/static/description/index.html
odoo/addons/stock_push_delay/tests/__init__.py
odoo/addons/stock_push_delay/tests/test_stock_push_delay.py
odoo14_addon_stock_push_delay-14.0.1.0.2.dev5.dist-info/METADATA
odoo14_addon_stock_push_delay-14.0.1.0.2.dev5.dist-info/WHEEL
odoo14_addon_stock_push_delay-14.0.1.0.2.dev5.dist-info/top_level.txt
odoo14_addon_stock_push_delay-14.0.1.0.2.dev5.dist-info/RECORD
